SpatialTransform/__init__.py
SpatialTransform/lib/euler.py
SpatialTransform/lib/pose.py
SpatialTransform/lib/transform.py
SpatialTransform/tests/__init__.py
SpatialTransform/tests/test_euler.py
SpatialTransform/tests/test_hierarchy.py
SpatialTransform/tests/test_methods.py
SpatialTransform/tests/test_pose.py
SpatialTransform/tests/test_properties.py
SpatialTransform/tests/test_transform_extended.py
SpatialTransform/tests/utils.py
spatial_transform-1.3.3.dist-info/METADATA
spatial_transform-1.3.3.dist-info/WHEEL
spatial_transform-1.3.3.dist-info/licenses/LICENSE
spatial_transform-1.3.3.dist-info/RECORD
