Metadata-Version: 2.4
Name: spatial-transform
Version: 1.3.3
Summary: Transform hierarchies in 3D space.
Project-URL: Homepage, https://github.com/Wasserwecken/spatial-transform
Project-URL: Bug Tracker, https://github.com/Wasserwecken/spatial-transform/issues
Author-email: Wasserwecken <author@example.com>
License-File: LICENSE
Classifier: License :: OSI Approved :: MIT License
Classifier: Operating System :: OS Independent
Classifier: Programming Language :: Python :: 3
Requires-Python: >=3.9
Requires-Dist: pyglm==2.8.2
